{
  "project_info": {
    "project_number": "394342689792",
    "project_id": "cryptofile-android",
    "storage_bucket": "cryptofile-android.firebasestorage.app"
  },
  "client": [
    {
      "client_info": {
        "mobilesdk_app_id": "1:394342689792:android:1eb63ff5f03c52abcd3ce5",
        "android_client_info": {
          "package_name": "com.example.cryptofile_android"
        }
      },
      "oauth_client": [],
      "api_key": [
        {
          "current_key": "AIzaSyCKwhHQ6D3gBldGoMOALgmMXpdijLfLcCs"
        }
      ],
      "services": {
        "appinvite_service": {
          "other_platform_oauth_client": []
        }
      }
    }
  ],
  "configuration_version": "1"
}